truhanen/windowlayouts/__init__.py
truhanen/windowlayouts/windowlayouts.py
truhanen_windowlayouts-1.0.6.dist-info/LICENSE
truhanen_windowlayouts-1.0.6.dist-info/METADATA
truhanen_windowlayouts-1.0.6.dist-info/WHEEL
truhanen_windowlayouts-1.0.6.dist-info/entry_points.txt
truhanen_windowlayouts-1.0.6.dist-info/RECORD
