Metadata-Version: 2.1
Name: truhanen-windowlayouts
Version: 1.0.6
Summary: Utility for storing & restoring window layouts on the X Window System
Home-page: https://github.com/truhanen/windowlayouts
License: MIT
Author: Tuukka Ruhanen
Author-email: tuukka.t.ruhanen@gmail.com
Requires-Python: >=3.7.1,<4.0.0
Classifier: License :: OSI Approved :: MIT License
Classifier: Programming Language :: Python :: 3
Classifier: Programming Language :: Python :: 3.8
Classifier: Programming Language :: Python :: 3.9
Classifier: Programming Language :: Python :: 3.10
Classifier: Programming Language :: Python :: 3.11
Classifier: Programming Language :: Python :: 3.7
Classifier: Topic :: Utilities
Provides-Extra: pandas
Requires-Dist: appdirs (>=1.4.4,<2.0.0)
Requires-Dist: dataclasses-json (>=0.5.2,<0.6.0)
Requires-Dist: pandas (>=1.2.3,<2.0.0) ; extra == "pandas"
Project-URL: Repository, https://github.com/truhanen/windowlayouts
